{"anzahl307": {"received": 28, "sent": 29}, "anzahl305": {"received": 22, "sent": 9}, "anzahl225": {"received": 22, "sent": 9}, "tele/gosund_r019_1/LWT": {"received": 21, "sent": 9}, "tele/gosund_r019_2/LWT": {"received": 21, "sent": 9}, "tele/tasmota_16C491/LWT": {"received": 21, "sent": 9}, "tele/tasmota_16C491/)/LWT": {"received": 21, "sent": 9}, "tele/tasmota_CDA543/LWT": {"received": 21, "sent": 9}, "tele/tasmota_16C550/LWT": {"received": 21, "sent": 9}, "tele/tasmota_CDA5E8/LWT": {"received": 21, "sent": 9}, "tele/tasmota_CDA5E6/LWT": {"received": 21, "sent": 9}, "tele/tasmota_CDA5E6/)/LWT": {"received": 21, "sent": 9}, "tele/tasmota_16C37F/LWT": {"received": 21, "sent": 9}, "tele/tasmota_16C227/LWT": {"received": 21, "sent": 11}, "tele/tasmota_CDA75E/LWT": {"received": 21, "sent": 10}, "tele/tasmota_CDA757/LWT": {"received": 21, "sent": 19}, "tele/tasmota_16C1E6/LWT": {"received": 21, "sent": 10}, "tele/tasmota_CDA83D/LWT": {"received": 20, "sent": 9}, "tele/tasmota_16C192/LWT": {"received": 20, "sent": 10}, "tele/baumi/LWT": {"received": 20, "sent": 9}, "tele/test/LWT": {"received": 20, "sent": 9}, "tele/baumgaertner/LWT": {"received": 20, "sent": 9}, "tasmota/discovery/DC4F229C9E56/config": {"received": 19, "sent": 9}, "tasmota/discovery/DC4F229C9E56/sensors": {"received": 19, "sent": 18}, "tasmota/discovery/40F520EBA051/config": {"received": 19, "sent": 9}, "tasmota/discovery/40F520EBA051/sensors": {"received": 19, "sent": 9}, "tasmota/discovery/40F520EB3CAB/config": {"received": 19, "sent": 9}, "tasmota/discovery/40F520EB3CAB/sensors": {"received": 19, "sent": 9}, "tasmota/discovery/48551917F32C/config": {"received": 19, "sent": 9}, "tasmota/discovery/48551917F32C/sensors": {"received": 19, "sent": 9}, "tasmota/discovery/48551917AEF0/config": {"received": 19, "sent": 9}, "tasmota/discovery/48551917AEF0/sensors": {"received": 19, "sent": 9}, "tasmota/discovery/48CA439B5A8C/config": {"received": 19, "sent": 9}, "tasmota/discovery/48CA439B5A8C/sensors": {"received": 19, "sent": 9}, "tasmota/discovery/98F4ABFB0921/config": {"received": 19, "sent": 13}, "tasmota/discovery/98F4ABFB0921/sensors": {"received": 19, "sent": 15}, "tasmota/discovery/5CCF7F16C491/config": {"received": 19, "sent": 9}, "tasmota/discovery/5CCF7F16C491/sensors": {"received": 19, "sent": 10}, "tasmota/discovery/18FE34CDA543/config": {"received": 19, "sent": 9}, "tasmota/discovery/18FE34CDA543/sensors": {"received": 19, "sent": 10}, "tasmota/discovery/5CCF7F16C550/config": {"received": 19, "sent": 9}, "tasmota/discovery/5CCF7F16C550/sensors": {"received": 19, "sent": 9}, "tasmota/discovery/18FE34CDA5E8/config": {"received": 19, "sent": 9}, "tasmota/discovery/18FE34CDA5E8/sensors": {"received": 19, "sent": 9}, "tasmota/discovery/18FE34CDA5E6/config": {"received": 18, "sent": 14}, "tasmota/discovery/18FE34CDA5E6/sensors": {"received": 19, "sent": 13}, "tasmota/discovery/5CCF7F16C37F/config": {"received": 18, "sent": 9}, "tasmota/discovery/5CCF7F16C37F/sensors": {"received": 18, "sent": 12}, "tasmota/discovery/5CCF7F16C227/config": {"received": 17, "sent": 9}, "tasmota/discovery/5CCF7F16C227/sensors": {"received": 17, "sent": 9}, "tasmota/discovery/18FE34CDA75E/config": {"received": 17, "sent": 9}, "tasmota/discovery/18FE34CDA75E/sensors": {"received": 17, "sent": 9}, "tasmota/discovery/18FE34CDA757/config": {"received": 16, "sent": 8}, "tasmota/discovery/18FE34CDA757/sensors": {"received": 16, "sent": 8}, "tasmota/discovery/5CCF7F16C1E6/config": {"received": 16, "sent": 8}, "tasmota/discovery/5CCF7F16C1E6/sensors": {"received": 15, "sent": 8}, "tasmota/discovery/18FE34CDA83D/config": {"received": 15, "sent": 8}, "tasmota/discovery/18FE34CDA83D/sensors": {"received": 15, "sent": 8}, "tasmota/discovery/5CCF7F16C192/config": {"received": 15, "sent": 8}, "tasmota/discovery/5CCF7F16C192/sensors": {"received": 15, "sent": 8}, "luftfeuchteserverraum": {"received": 15, "sent": 8}, "temperaturserverraum": {"received": 143, "sent": 8}, "nous/timer02/tele/LWT": {"received": 14, "sent": 8}, "nous/timer01/tele/LWT": {"received": 14, "sent": 8}, "smart_wvss/steckdose_ap314/tele/LWT": {"received": 14, "sent": 8}, "smart_wvss/hochbeet_master/tele/LWT": {"received": 14, "sent": 8}, "sensoren/Sensor_Spi/tele/LWT": {"received": 14, "sent": 8}, "e3fs1/pomi": {"received": 14, "sent": 8}, "e3fs1/pomi/ip": {"received": 14, "sent": 8}, "e3fs1/pomi/pub": {"received": 14, "sent": 8}, "e3fs1/pomi/net": {"received": 14, "sent": 8}, "e3fs1/pomi/xD": {"received": 14, "sent": 8}, "e3fs1/pomi/local": {"received": 14, "sent": 8}, "e3fs1/xD": {"received": 14, "sent": 8}, "e3fs1/e_a/local": {"received": 14, "sent": 8}, "e3fs1/e_a/ip": {"received": 14, "sent": 8}, "e3fs1/e_a/pub": {"received": 14, "sent": 8}, "e3fs1/e_a/net": {"received": 14, "sent": 8}, "e3fs1/123": {"received": 14, "sent": 8}, "e3fs2/pomi/ip": {"received": 14, "sent": 8}, "e3fs2/pomi/net": {"received": 14, "sent": 8}, "e3fs2/pomi/localip": {"received": 14, "sent": 8}, "e3fs2/pomi/pub": {"received": 14, "sent": 8}, "e3fs2/pomi/local": {"received": 14, "sent": 8}, "e3fs2/malu/pub": {"received": 14, "sent": 8}, "e3fs2/malu/ip": {"received": 14, "sent": 8}, "e3fs2/malu/net": {"received": 14, "sent": 8}, "e3fs2/malu/localip": {"received": 14, "sent": 8}, "e3fs2/riehlegro\u00dfkinsky/pub": {"received": 14, "sent": 8}, "e3fs2/marc/ip": {"received": 14, "sent": 8}, "e3fs2/marc/pub": {"received": 14, "sent": 8}, "e3fs2/marc/local": {"received": 14, "sent": 8}, "e3fs2/marc/net": {"received": 14, "sent": 8}, "e3fs2/riehlegrosskinsky/pub": {"received": 14, "sent": 8}, "e3fs2/riehlegrosskinsky/ip": {"received": 14, "sent": 8}, "e3fs2/riehlegrosskinsky/local": {"received": 14, "sent": 8}, "e3fs2/riehlegrosskinsky/net": {"received": 14, "sent": 8}, "e3fs2/sam/pub": {"received": 14, "sent": 8}, "e3fs2/sam/ip": {"received": 14, "sent": 8}, "e3fs2/sam/net": {"received": 14, "sent": 8}, "e3fs2/sam/localip": {"received": 14, "sent": 8}, "e3fs2/LarsJosef/pub": {"received": 14, "sent": 8}, "e3fs2/LarsJosef/ip": {"received": 14, "sent": 8}, "e3fs2/LarsJosef/local": {"received": 14, "sent": 8}, "e3fs2/tim/ip": {"received": 14, "sent": 8}, "e3fs2/tim/net": {"received": 14, "sent": 8}, "e3fs2/tim/local": {"received": 14, "sent": 8}, "e3fs2/tim/pub": {"received": 14, "sent": 8}, "e3fs3/pomi/ip": {"received": 14, "sent": 8}, "e3fs3/pomi/local": {"received": 14, "sent": 8}, "e3fs3/pomi/vpnip": {"received": 14, "sent": 8}, "e3fs3/pomi/public": {"received": 14, "sent": 8}, "e3fs3/niklas/ip": {"received": 14, "sent": 8}, "e3fs3/niklas/local": {"received": 14, "sent": 8}, "e3fs3/niklas/vpnip": {"received": 14, "sent": 8}, "e3fs3/niklas/public": {"received": 14, "sent": 8}, "e3fs3/lauer/ip": {"received": 14, "sent": 8}, "e3fs3/lauer/local": {"received": 14, "sent": 8}, "e3fs3/lauer/vpnip": {"received": 14, "sent": 8}, "e3fs3/lauer/public": {"received": 14, "sent": 8}, "e2fs1/LWT": {"received": 14, "sent": 8}, "sadi/LWT": {"received": 14, "sent": 8}, "e2fs1tele/tasmota_CDA757/LWT": {"received": 14, "sent": 8}, "baumgaertner/LWT": {"received": 14, "sent": 8}, "nous/timer01/tele/STATE": {"received": 3, "sent": 2}, "nous/timer01/tele/SENSOR": {"received": 3, "sent": 2}, "smart_wvss/steckdose_ap314/tele/STATE": {"received": 42, "sent": 8}, "smart_wvss/steckdose_ap314/tele/SENSOR": {"received": 42, "sent": 8}, "tele/baumgaertner/STATE": {"received": 2, "sent": 0}, "tele/baumgaertner/SENSOR": {"received": 115, "sent": 1000}, "tele/345picX/LWT": {"received": 18, "sent": 9}, "tele/gosund_r019_2/STATE": {"received": 2, "sent": 0}, "tele/gosund_r019_2/SENSOR": {"received": 2, "sent": 0}, "tele/gosund_r019_1/STATE": {"received": 1, "sent": 0}, "tele/gosund_r019_1/SENSOR": {"received": 1, "sent": 0}, "nous/timer02/tele/STATE": {"received": 1, "sent": 0}, "nous/timer02/tele/SENSOR": {"received": 1, "sent": 0}}